README.md
setup.py
ltexpect/__init__.py
ltexpect/__main__.py
ltexpect/ltexpect.py
ltexpect.egg-info/PKG-INFO
ltexpect.egg-info/SOURCES.txt
ltexpect.egg-info/dependency_links.txt
ltexpect.egg-info/entry_points.txt
ltexpect.egg-info/requires.txt
ltexpect.egg-info/top_level.txt