Metadata-Version: 2.1
Name: ltexpect
Version: 1.0.3
Summary: Easier Expect interface
Home-page: https://github.com/laowangv5/ltexpect
Author: Yonghang Wang
Author-email: yhang_wang@icloud.com
License: MIT
Keywords: ltexpect,liteexpect,expect,lexpect,ltexpect,LiteExpect,Expect
Platform: UNKNOWN
Classifier: License :: OSI Approved :: MIT License
